kraken_analytics_rmq/__init__.py
kraken_analytics_rmq-1.0.2.dist-info/LICENSE
kraken_analytics_rmq-1.0.2.dist-info/WHEEL
kraken_analytics_rmq-1.0.2.dist-info/METADATA
kraken_analytics_rmq-1.0.2.dist-info/RECORD
