Metadata-Version: 2.1
Name: kraken-analytics-rmq
Version: 1.0.2
Summary: kraken analytics rabbitmq client
Home-page: https://github.com/stakkle5/kraken-analytics-rmq
License: MIT
Keywords: kraken,kraken-analytics,rmq
Author: Thomas
Author-email: thomas@kraken-analytics.io
Requires-Python: >=3.11,<4.0
Classifier: License :: OSI Approved :: MIT License
Classifier: Programming Language :: Python :: 3
Classifier: Programming Language :: Python :: 3.11
Requires-Dist: pika (>=1.3.2,<2.0.0)
Project-URL: Repository, https://github.com/stakkle5/kraken-analytics-rmq
